[
  {
    "MapID": 10000,
    "Size": {
      "Width": 50,
      "Height": 50
    },
    "Grid": {
      "Width": 100,
      "Height": 100
    },
    "DeployList": [
      "1"
    ],
    "MaxDeployNpcCount": 10
  },
  {
    "MapID": 10001,
    "Size": {
      "Width": 50,
      "Height": 50
    },
    "Grid": {
      "Width": 100,
      "Height": 100
    },
    "DeployList": [
      "2",
      "3",
      "4",
      "5",
      "6"
    ],
    "MaxDeployNpcCount": 10
  },
  {
    "MapID": 50000,
    "Size": {
      "Width": 50,
      "Height": 50
    },
    "Grid": {
      "Width": 100,
      "Height": 100
    },
    "DeployList": [
      "3"
    ],
    "MaxDeployNpcCount": 10
  },
  {
    "MapID": 50001,
    "Size": {
      "Width": 50,
      "Height": 50
    },
    "Grid": {
      "Width": 100,
      "Height": 100
    },
    "DeployList": [
      "4"
    ],
    "MaxDeployNpcCount": 10
  },
  {
    "MapID": 99999,
    "Size": {
      "Width": 10,
      "Height": 10
    },
    "Grid": {
      "Width": 50,
      "Height": 50
    },
    "DeployList": [
      "666"
    ],
    "MaxDeployNpcCount": 0
  }



]